mpylogs/__init__.py
mpylogs/functions.py
mpylogs-0.1.0.dist-info/METADATA
mpylogs-0.1.0.dist-info/WHEEL
mpylogs-0.1.0.dist-info/top_level.txt
mpylogs-0.1.0.dist-info/RECORD
