Metadata-Version: 2.1
Name: mpylogs
Version: 0.1.0
Summary: Python library for logging with colors and http status code.
Home-page: https://github.com/jeniferss/_logging
License: MIT
Keywords: logs logging logger
Classifier: Intended Audience :: Developers
Classifier: Programming Language :: Python
Classifier: Programming Language :: Python :: 3.10
Requires-Python: >=3.10
